muxllm/__init__.py
muxllm/llm.py
muxllm/prompt.py
muxllm/tools.py
muxllm/providers/__init__.py
muxllm/providers/base.py
muxllm/providers/factory.py
muxllm/providers/panthropic.py
muxllm/providers/pfireworks.py
muxllm/providers/pgoogle.py
muxllm/providers/pgroq.py
muxllm/providers/plocal.py
muxllm/providers/popenai.py
muxllm-1.0.2.dist-info/LICENSE
muxllm-1.0.2.dist-info/METADATA
muxllm-1.0.2.dist-info/WHEEL
muxllm-1.0.2.dist-info/top_level.txt
muxllm-1.0.2.dist-info/RECORD
