Metadata-Version: 2.1
Name: muxllm
Version: 1.0.2
Summary: muxllm is a python library designed to be an all-in-one wrapper for various cloud providers as well as local inference.
Author-email: Mannan Bhardwaj <mannanb728@gmail.com>
License: MIT License
Project-URL: Homepage, https://github.com/MannanB/MUXLLM
Keywords: llm,gpt,wrapper,api
Classifier: License :: OSI Approved :: MIT License
Classifier: Programming Language :: Python
Classifier: Programming Language :: Python :: 3
Requires-Python: >=3.9
License-File: LICENSE
Requires-Dist: openai
Requires-Dist: groq
Requires-Dist: anthropic
Requires-Dist: google-generativeai
